dbu/__init__.py
dbu/dbcore.py
dbu/dbutils.py
dbu-0.0.2.dist-info/LICENSE
dbu-0.0.2.dist-info/METADATA
dbu-0.0.2.dist-info/WHEEL
dbu-0.0.2.dist-info/top_level.txt
dbu-0.0.2.dist-info/RECORD
