Metadata-Version: 2.1
Name: dbu
Version: 0.0.2
Summary: DB Utils
Home-page: https://github.com/leonmaks/dbu
Author: Leon Maksim
Author-email: le_ma_@mail.ru
License: UNKNOWN
Platform: UNKNOWN
Classifier: Programming Language :: Python :: 3
Classifier: License :: OSI Approved :: MIT License
Classifier: Operating System :: OS Independent
